fastcaptcha/__init__.py
fastcaptcha/exeptions.py
fastcaptcha/helpers.py
fastcaptcha_python-1.1.0.dist-info/METADATA
fastcaptcha_python-1.1.0.dist-info/WHEEL
fastcaptcha_python-1.1.0.dist-info/RECORD
