Metadata-Version: 2.1
Name: fastcaptcha-python
Version: 1.1.0
Summary: Fastcaptcha solve recaptchaV2, recaptchaV3, funcaptcha, imageToText very fast and cheap
Home-page: https://fastcaptcha.ru
License: MIT
Keywords: fastcaptcha,recaptcha,recaptchav3,funcaptcha,imagetotext,solver captcha,recaptcha solver,funcaptcha solver,recaptcha recognition
Author: Fastcaptcha
Author-email: support@fastcaptcha.ru
Requires-Python: >=3.7,<4.0
Classifier: License :: OSI Approved :: MIT License
Classifier: Programming Language :: Python :: 3
Classifier: Programming Language :: Python :: 3.7
Classifier: Programming Language :: Python :: 3.8
Classifier: Programming Language :: Python :: 3.9
Classifier: Programming Language :: Python :: 3.10
Classifier: Programming Language :: Python :: 3.11
Requires-Dist: requests (>=2.31.0,<3.0.0)
